gaji/__init__.py
gaji-0.0.0.dist-info/LICENSE
gaji-0.0.0.dist-info/METADATA
gaji-0.0.0.dist-info/WHEEL
gaji-0.0.0.dist-info/top_level.txt
gaji-0.0.0.dist-info/RECORD
