Metadata-Version: 2.1
Name: gaji
Version: 0.0.0
Summary: class-based web framework
Home-page: https://github.com/akiacode/gaji
Author: Catry
License: MIT
Project-URL: Bug Tracker, https://github.com/akiacode/gaji/issues
Platform: UNKNOWN
Classifier: Programming Language :: Python :: 3
Classifier: License :: OSI Approved :: MIT License
Classifier: Operating System :: OS Independent
Requires-Python: >=3.6
License-File: LICENSE
